maracas/__init__.py
maracas/dataset.py
maracas/maracas.py
maracas/utils.py
maracas-0.0.1.dist-info/LICENSE
maracas-0.0.1.dist-info/METADATA
maracas-0.0.1.dist-info/WHEEL
maracas-0.0.1.dist-info/top_level.txt
maracas-0.0.1.dist-info/RECORD
