Metadata-Version: 2.1
Name: maracas
Version: 0.0.1
Summary: Tools for generating noisy and reverberant audio files
Home-page: UNKNOWN
License: UNKNOWN
Platform: UNKNOWN
Requires-Dist: numpy
Requires-Dist: scipy
Requires-Dist: numba
Requires-Dist: tqdm
